mocksmith/__init__.py
mocksmith/annotations.py
mocksmith/decorators.py
mocksmith/mock_builder.py
mocksmith/mock_factory.py
mocksmith/pydantic_integration.py
mocksmith/specialized/__init__.py
mocksmith/specialized/contact.py
mocksmith/specialized/geographic.py
mocksmith/types/__init__.py
mocksmith/types/binary.py
mocksmith/types/boolean.py
mocksmith/types/numeric.py
mocksmith/types/string.py
mocksmith/types/temporal.py
mocksmith-7.1.0.dist-info/METADATA
mocksmith-7.1.0.dist-info/WHEEL
mocksmith-7.1.0.dist-info/licenses/LICENSE
mocksmith-7.1.0.dist-info/RECORD
