Metadata-Version: 2.4
Name: mocksmith
Version: 7.1.0
Summary: Type-safe data validation and mocking for Python dataclasses and Pydantic models
License: MIT
License-File: LICENSE
Keywords: mock,validation,dataclass,pydantic,testing,faker,types,sql
Author: Gurmeet Saran
Author-email: gurmeetx@gmail.com
Requires-Python: >=3.9
Classifier: Development Status :: 4 - Beta
Classifier: Intended Audience :: Developers
Classifier: License :: OSI Approved :: MIT License
Classifier: Programming Language :: Python :: 3
Classifier: Programming Language :: Python :: 3.9
Classifier: Programming Language :: Python :: 3.10
Classifier: Programming Language :: Python :: 3.11
Classifier: Programming Language :: Python :: 3.12
Classifier: Programming Language :: Python :: 3.13
Classifier: Programming Language :: Python :: 3.14
Classifier: Topic :: Database
Classifier: Topic :: Software Development :: Libraries :: Python Modules
Classifier: Typing :: Typed
Provides-Extra: pydantic
Requires-Dist: faker (>=33.2,<38.0)
Project-URL: Bug Tracker, https://github.com/gurmeetsaran/mocksmith/issues
Project-URL: Homepage, https://github.com/gurmeetsaran/mocksmith
Project-URL: Repository, https://github.com/gurmeetsaran/mocksmith
